{"chunk_definitions":[{"row":284,"row_count":1,"visible":true,"expansion_state":0,"options":{"engine":"r","label":"running-box-pace","content":"valuebox","title":"Average Pace","dev":"png"},"document_id":"78B8FA42","chunk_id":"c2x3e37zybp80","chunk_label":"running-box-pace"},{"row":467,"row_count":1,"visible":true,"expansion_state":0,"options":{"engine":"r","label":"cycling-box-pace","content":"valuebox","title":"Average Speed","dev":"png"},"document_id":"78B8FA42","chunk_id":"c4pozwptud9q1","chunk_label":"cycling-box-pace"},{"row":651,"row_count":1,"visible":true,"expansion_state":0,"options":{"engine":"r","label":"swimming-box-pace","content":"valuebox","title":"Average Pace","dev":"png"},"document_id":"78B8FA42","chunk_id":"cq21vkqsnn5kd","chunk_label":"swimming-box-pace"}],"doc_write_time":1745670471}